[{"id":"unitile","name":"Unitile","name_ru":"Юнайтед Таил (Уралкерамика)","type":"Российский","description":"Группа компаний: Шахтинская керамика (19.5 млн м²/год) + Воронежская керамика (8 млн м²/год)","plants":"Челябинск","production_capacity":"27.50","market_share_pct":"36.70","segments":["керамогранит","клинкер","фасадная плитка","плитка для пола"],"brands":["Unitile"],"website":"https://unitile.ru","founded_year":2008,"employees_est":1800,"revenue_est":"~12 млрд руб (оценка)","source":"unitile.ru/about/","notes":"Общая мощность группы 27.5 млн м²/год. Источники: unitile.ru/about/","created_at":"2026-05-11T14:11:52.816Z"},{"id":"estima","name":"Estima","name_ru":"Эстима","type":"Российский","description":"Крупный производитель керамогранита. Акцент на крупноформатный керамогранит до 160×320 см. Собственная сырьевая база.","plants":"Саратов, Пугачёв (Саратовская обл.)","production_capacity":"15.00","market_share_pct":"20.00","segments":["керамогранит","плитка для пола","фасадный керамогранит"],"brands":["Estima","Estima Stone"],"website":"https://estima.ru","founded_year":2004,"employees_est":2200,"revenue_est":"~16 млрд руб (оценка)","source":"estima.ru/about/","notes":"15 млн м² керамогранита в год. Источник: estima.ru/about/","created_at":"2026-05-11T14:11:52.815Z"},{"id":"kerama_marazzi","name":"Kerama Marazzi","name_ru":"Керама Марацци","type":"Международный (итальяно-российский)","description":"Крупнейший производитель. 3 производственных комплекса: Орёл (плитка, керамогранит), Малино (крупноформатный керамогранит Continua+), Орёл (сантехника). Входит в итальянскую группу Marazzi.","plants":"Орёл (2 завода: плитка + сантехника), Малино (МО)","production_capacity":"32.40","market_share_pct":"43.30","segments":["плитка для стен","керамогранит","сантехника","декор/мозаика"],"brands":["Kerama Marazzi","Marazzi"],"website":"https://kerama-marazzi.com","founded_year":1992,"employees_est":6500,"revenue_est":"~55 млрд руб (оценка)","source":"kerama-marazzi.com/about/","notes":"32.4 млн м² плитки и керамогранита в 2025 г. Источник: kerama-marazzi.com/about/","created_at":"2026-05-11T14:11:52.813Z"},{"id":"shakhty","name":"Shakhtinskaya Plitka","name_ru":"Шахтинская плитка","type":"Российский","description":"Входит в группу компаний Unitile. Производит облицовочную плитку и керамогранит.","plants":"Шахты (Ростовская обл.)","production_capacity":"19.50","market_share_pct":"0.00","segments":["плитка для стен","плитка для пола"],"brands":["Шахтинская плитка"],"website":"https://shakhty-plitka.ru","founded_year":1995,"employees_est":1200,"revenue_est":"~6 млрд руб (оценка)","source":"unitile.ru/about/","notes":"Завод группы Unitile. Мощность 19.5 млн м²/год. Источник: unitile.ru/about/","created_at":"2026-05-11T14:11:52.816Z"},{"id":"cersanit","name":"Cersanit","name_ru":"Церсанит (Lasselsberger)","type":"Международный (польский)","description":"Польская компания, входит в группу Lasselsberger. Локализованные заводы в РФ. Производит плитку и сантехнику.","plants":"Сычёвка (Смоленская обл.), Сланцы (Ленинградская обл.)","production_capacity":null,"market_share_pct":"0.00","segments":["плитка для стен","плитка для пола","керамогранит","сантехника"],"brands":["Cersanit","Lasselsberger"],"website":"https://cersanit.ru","founded_year":1993,"employees_est":3500,"revenue_est":"~16 млрд руб (оценка)","source":"alto-group.ru (2024)","notes":"Нет подтверждённых данных об объёме производства","created_at":"2026-05-11T14:11:52.814Z"},{"id":"kpz","name":"Kirov Ceramics","name_ru":"Кировский керамический завод","type":"Российский","description":"Крупный производитель в Приволжье. Плитка для стен и пола. Активно развивает дизайнерские коллекции.","plants":"Киров","production_capacity":null,"market_share_pct":"0.00","segments":["плитка для стен","плитка для пола"],"brands":["ККЗ","Kirov Ceramics"],"website":"https://kkz-kirov.ru","founded_year":1962,"employees_est":900,"revenue_est":"~4 млрд руб (оценка)","source":"alto-group.ru (2024)","notes":"Нет подтверждённых данных об объёме производства","created_at":"2026-05-11T14:11:52.817Z"},{"id":"sokol","name":"Sokol Ceramics","name_ru":"Сокол (Сокольский керамический)","type":"Российский","description":"Один из старейших заводов (основан в 1956, Липецкая обл.). Модернизирован в 2010-х.","plants":"Сокол (Липецкая обл.)","production_capacity":null,"market_share_pct":"0.00","segments":["плитка для стен","плитка для пола","керамогранит"],"brands":["Sokol Ceramics"],"website":"https://sokol-ceramics.ru","founded_year":1956,"employees_est":1500,"revenue_est":"~8 млрд руб (оценка)","source":"alto-group.ru (2024)","notes":"Нет подтверждённых данных об объёме производства","created_at":"2026-05-11T14:11:52.815Z"},{"id":"volgograd","name":"Volgograd Ceramic Works","name_ru":"Волгоградский керамический завод","type":"Российский","description":"Один из старейших заводов Поволжья. Модернизация. Инвестиционный проект до 2028.","plants":"Волгоград","production_capacity":null,"market_share_pct":"0.00","segments":["плитка для стен","плитка для пола","керамогранит"],"brands":["ВКЗ"],"website":"https://volgo-keram.ru","founded_year":1970,"employees_est":1000,"revenue_est":"~5 млрд руб (оценка)","source":"investprojects.info (2023)","notes":"Нет подтверждённых данных об объёме производства","created_at":"2026-05-11T14:11:52.817Z"}]